{"stat.mineBlock.minecraft.log":117,"stat.useItem.minecraft.diamond_pickaxe":990,"achievement.exploreAllBiomes":{"value":0,"progress":["Deep Ocean","Ocean","Beach","Plains"]},"achievement.openInventory":9,"stat.enderchestOpened":1,"stat.climbOneCm":6006,"stat.talkedToVillager":1,"stat.fallOneCm":691,"stat.mineBlock.minecraft.iron_ore":142,"stat.flyOneCm":22594,"stat.mineBlock.minecraft.gold_ore":98,"stat.timeSinceDeath":14083,"stat.leaveGame":1,"stat.playOneMinute":14083,"stat.jump":79,"stat.useItem.minecraft.diamond_axe":117,"stat.mineBlock.minecraft.stone":426,"stat.walkOneCm":98836,"stat.mineBlock.minecraft.iron_block":96,"stat.mineBlock.minecraft.coal_ore":228,"stat.sprintOneCm":76771}